<LanguagePoiConfiguration xmlns:xsi="http://www.w3.org/2001/XMLSchema-instance" xsi:noNamespaceSchemaLocation="xsd/locale/LanguagePoiConfiguration.xsd" version="1">
  <!--Alphabetically sorted setup category definitions for each fuel type, will be reloaded after language change-->
  <SetupCategoryDefinition>
    <PoiCategoryMapping fueltype="default">
      <PoiCategoryRef>1</PoiCategoryRef>
      <!--Autostadt-->
      <PoiCategoryRef>12</PoiCategoryRef>
      <!--SEAT Дилеры-->
      <PoiCategoryRef>11</PoiCategoryRef>
      <!--SEAT Сервисные центры-->
      <PoiCategoryRef>18</PoiCategoryRef>
      <!--Автобусные остановки-->
      <PoiCategoryRef>4</PoiCategoryRef>
      <!--АГЗС (природный газ)-->
      <PoiCategoryRef>3</PoiCategoryRef>
      <!--АГЗС (сжиж. нефт. газ)-->
      <PoiCategoryRef>5</PoiCategoryRef>
      <!--АЗС-->
      <PoiCategoryRef>23</PoiCategoryRef>
      <!--Аптеки-->
      <PoiCategoryRef>2</PoiCategoryRef>
      <!--Аэропорты-->
      <PoiCategoryRef>45</PoiCategoryRef>
      <!--Банки-->
      <PoiCategoryRef>25</PoiCategoryRef>
      <!--Банкоматы-->
      <PoiCategoryRef>21</PoiCategoryRef>
      <!--Больницы-->
      <PoiCategoryRef>30</PoiCategoryRef>
      <!--Вина и крепкие напитки-->
      <PoiCategoryRef>41</PoiCategoryRef>
      <!--Гольф-->
      <PoiCategoryRef>33</PoiCategoryRef>
      <!--Достопримечательн.-->
      <PoiCategoryRef>16</PoiCategoryRef>
      <!--Ж/д вокзалы-->
      <PoiCategoryRef>55</PoiCategoryRef>
      <!--Зарядные станции-->
      <PoiCategoryRef>19</PoiCategoryRef>
      <!--Инф. для туристов-->
      <PoiCategoryRef>35</PoiCategoryRef>
      <!--Казино-->
      <PoiCategoryRef>26</PoiCategoryRef>
      <!--Кафе-->
      <PoiCategoryRef>34</PoiCategoryRef>
      <!--Кинотеатры-->
      <PoiCategoryRef>54</PoiCategoryRef>
      <!--Кладбища-->
      <PoiCategoryRef>48</PoiCategoryRef>
      <!--Конгресс-центры-->
      <PoiCategoryRef>42</PoiCategoryRef>
      <!--Лодочный спорт-->
      <PoiCategoryRef>43</PoiCategoryRef>
      <!--Лыжи-->
      <PoiCategoryRef>22</PoiCategoryRef>
      <!--Медицинск.учреждения-->
      <PoiCategoryRef>37</PoiCategoryRef>
      <!--Музеи-->
      <PoiCategoryRef>31</PoiCategoryRef>
      <!--Ночная жизнь-->
      <PoiCategoryRef>52</PoiCategoryRef>
      <!--Образоват. учреждения-->
      <PoiCategoryRef>28</PoiCategoryRef>
      <!--Одежда-->

      <!--Органы самоуправлен.-->
      <PoiCategoryRef>46</PoiCategoryRef>
      <!--Отделения связи-->
      <PoiCategoryRef>8</PoiCategoryRef>
      <!--Отели и мотели-->
      <PoiCategoryRef>38</PoiCategoryRef>
      <!--Памятники-->
      <PoiCategoryRef>32</PoiCategoryRef>
      <!--Парки-->
      <PoiCategoryRef>44</PoiCategoryRef>
      <!--Парки культ. и отдыха-->
      <PoiCategoryRef>9</PoiCategoryRef>
      <!--Паромы-->

      <!--Пересечения автомаг.-->
      <PoiCategoryRef>10</PoiCategoryRef>
      <!--Погранпереходы-->
      <PoiCategoryRef>20</PoiCategoryRef>
      <!--Полиция/милиция-->
      <PoiCategoryRef>50</PoiCategoryRef>
      <!--Посольства-->
      <PoiCategoryRef>49</PoiCategoryRef>
      <!--Правит., органы управл.-->
      <PoiCategoryRef>15</PoiCategoryRef>
      <!--Прокат автомобилей-->
      <PoiCategoryRef>24</PoiCategoryRef>
      <!--Рестораны-->
      <PoiCategoryRef>39</PoiCategoryRef>
      <!--Спортивные центры-->

      <!--Спортивный аэродром-->
      <PoiCategoryRef>6</PoiCategoryRef>
      <!--Стоянки-->
      <PoiCategoryRef>14</PoiCategoryRef>
      <!--Съезды/въезды автом.-->
      <PoiCategoryRef>36</PoiCategoryRef>
      <!--Театры, концерт. залы-->
      <PoiCategoryRef>27</PoiCategoryRef>
      <!--Торговые центры-->
      <PoiCategoryRef>7</PoiCategoryRef>
      <!--У автомагистралей-->
      <PoiCategoryRef>47</PoiCategoryRef>
      <!--Фирмы-->
      <PoiCategoryRef>53</PoiCategoryRef>
      <!--Церкви-->
      <PoiCategoryRef>29</PoiCategoryRef>
      <!--Электроника-->
    </PoiCategoryMapping>
    <PoiCategoryMapping fueltype="gasoline">
      <PoiCategoryRef>1</PoiCategoryRef>
      <!--Autostadt-->
      <PoiCategoryRef>12</PoiCategoryRef>
      <!--SEAT Дилеры-->
      <PoiCategoryRef>11</PoiCategoryRef>
      <!--SEAT Сервисные центры-->
      <PoiCategoryRef>18</PoiCategoryRef>
      <!--Автобусные остановки-->
      <PoiCategoryRef>4</PoiCategoryRef>
      <!--АГЗС (природный газ)-->
      <PoiCategoryRef>3</PoiCategoryRef>
      <!--АГЗС (сжиж. нефт. газ)-->
      <PoiCategoryRef>5</PoiCategoryRef>
      <!--АЗС-->
      <PoiCategoryRef>23</PoiCategoryRef>
      <!--Аптеки-->
      <PoiCategoryRef>2</PoiCategoryRef>
      <!--Аэропорты-->
      <PoiCategoryRef>45</PoiCategoryRef>
      <!--Банки-->
      <PoiCategoryRef>25</PoiCategoryRef>
      <!--Банкоматы-->
      <PoiCategoryRef>21</PoiCategoryRef>
      <!--Больницы-->
      <PoiCategoryRef>30</PoiCategoryRef>
      <!--Вина и крепкие напитки-->
      <PoiCategoryRef>41</PoiCategoryRef>
      <!--Гольф-->
      <PoiCategoryRef>33</PoiCategoryRef>
      <!--Достопримечательн.-->
      <PoiCategoryRef>16</PoiCategoryRef>
      <!--Ж/д вокзалы-->
      <PoiCategoryRef>55</PoiCategoryRef>
      <!--Зарядные станции-->
      <PoiCategoryRef>19</PoiCategoryRef>
      <!--Инф. для туристов-->
      <PoiCategoryRef>35</PoiCategoryRef>
      <!--Казино-->
      <PoiCategoryRef>26</PoiCategoryRef>
      <!--Кафе-->
      <PoiCategoryRef>34</PoiCategoryRef>
      <!--Кинотеатры-->
      <PoiCategoryRef>54</PoiCategoryRef>
      <!--Кладбища-->
      <PoiCategoryRef>48</PoiCategoryRef>
      <!--Конгресс-центры-->
      <PoiCategoryRef>42</PoiCategoryRef>
      <!--Лодочный спорт-->
      <PoiCategoryRef>43</PoiCategoryRef>
      <!--Лыжи-->
      <PoiCategoryRef>22</PoiCategoryRef>
      <!--Медицинск.учреждения-->
      <PoiCategoryRef>37</PoiCategoryRef>
      <!--Музеи-->
      <PoiCategoryRef>31</PoiCategoryRef>
      <!--Ночная жизнь-->
      <PoiCategoryRef>52</PoiCategoryRef>
      <!--Образоват. учреждения-->
      <PoiCategoryRef>28</PoiCategoryRef>
      <!--Одежда-->

      <!--Органы самоуправлен.-->
      <PoiCategoryRef>46</PoiCategoryRef>
      <!--Отделения связи-->
      <PoiCategoryRef>8</PoiCategoryRef>
      <!--Отели и мотели-->
      <PoiCategoryRef>38</PoiCategoryRef>
      <!--Памятники-->
      <PoiCategoryRef>32</PoiCategoryRef>
      <!--Парки-->
      <PoiCategoryRef>44</PoiCategoryRef>
      <!--Парки культ. и отдыха-->
      <PoiCategoryRef>9</PoiCategoryRef>
      <!--Паромы-->

      <!--Пересечения автомаг.-->
      <PoiCategoryRef>10</PoiCategoryRef>
      <!--Погранпереходы-->
      <PoiCategoryRef>20</PoiCategoryRef>
      <!--Полиция/милиция-->
      <PoiCategoryRef>50</PoiCategoryRef>
      <!--Посольства-->
      <PoiCategoryRef>49</PoiCategoryRef>
      <!--Правит., органы управл.-->
      <PoiCategoryRef>15</PoiCategoryRef>
      <!--Прокат автомобилей-->
      <PoiCategoryRef>24</PoiCategoryRef>
      <!--Рестораны-->
      <PoiCategoryRef>39</PoiCategoryRef>
      <!--Спортивные центры-->

      <!--Спортивный аэродром-->
      <PoiCategoryRef>6</PoiCategoryRef>
      <!--Стоянки-->
      <PoiCategoryRef>14</PoiCategoryRef>
      <!--Съезды/въезды автом.-->
      <PoiCategoryRef>36</PoiCategoryRef>
      <!--Театры, концерт. залы-->
      <PoiCategoryRef>27</PoiCategoryRef>
      <!--Торговые центры-->
      <PoiCategoryRef>7</PoiCategoryRef>
      <!--У автомагистралей-->
      <PoiCategoryRef>47</PoiCategoryRef>
      <!--Фирмы-->
      <PoiCategoryRef>53</PoiCategoryRef>
      <!--Церкви-->
      <PoiCategoryRef>29</PoiCategoryRef>
      <!--Электроника-->
    </PoiCategoryMapping>
    <PoiCategoryMapping fueltype="diesel">
      <PoiCategoryRef>23</PoiCategoryRef>
      <PoiCategoryRef>1</PoiCategoryRef>
      <!--Autostadt-->
      <PoiCategoryRef>12</PoiCategoryRef>
      <!--SEAT Дилеры-->
      <PoiCategoryRef>11</PoiCategoryRef>
      <!--SEAT Сервисные центры-->
      <PoiCategoryRef>18</PoiCategoryRef>
      <!--Автобусные остановки-->
      <PoiCategoryRef>4</PoiCategoryRef>
      <!--АГЗС (природный газ)-->
      <PoiCategoryRef>3</PoiCategoryRef>
      <!--АГЗС (сжиж. нефт. газ)-->
      <PoiCategoryRef>5</PoiCategoryRef>
      <!--АЗС-->
      <PoiCategoryRef>23</PoiCategoryRef>
      <!--Аптеки-->
      <PoiCategoryRef>2</PoiCategoryRef>
      <!--Аэропорты-->
      <PoiCategoryRef>45</PoiCategoryRef>
      <!--Банки-->
      <PoiCategoryRef>25</PoiCategoryRef>
      <!--Банкоматы-->
      <PoiCategoryRef>21</PoiCategoryRef>
      <!--Больницы-->
      <PoiCategoryRef>30</PoiCategoryRef>
      <!--Вина и крепкие напитки-->
      <PoiCategoryRef>41</PoiCategoryRef>
      <!--Гольф-->
      <PoiCategoryRef>33</PoiCategoryRef>
      <!--Достопримечательн.-->
      <PoiCategoryRef>16</PoiCategoryRef>
      <!--Ж/д вокзалы-->
      <PoiCategoryRef>55</PoiCategoryRef>
      <!--Зарядные станции-->
      <PoiCategoryRef>19</PoiCategoryRef>
      <!--Инф. для туристов-->
      <PoiCategoryRef>35</PoiCategoryRef>
      <!--Казино-->
      <PoiCategoryRef>26</PoiCategoryRef>
      <!--Кафе-->
      <PoiCategoryRef>34</PoiCategoryRef>
      <!--Кинотеатры-->
      <PoiCategoryRef>54</PoiCategoryRef>
      <!--Кладбища-->
      <PoiCategoryRef>48</PoiCategoryRef>
      <!--Конгресс-центры-->
      <PoiCategoryRef>42</PoiCategoryRef>
      <!--Лодочный спорт-->
      <PoiCategoryRef>43</PoiCategoryRef>
      <!--Лыжи-->
      <PoiCategoryRef>22</PoiCategoryRef>
      <!--Медицинск.учреждения-->
      <PoiCategoryRef>37</PoiCategoryRef>
      <!--Музеи-->
      <PoiCategoryRef>31</PoiCategoryRef>
      <!--Ночная жизнь-->
      <PoiCategoryRef>52</PoiCategoryRef>
      <!--Образоват. учреждения-->
      <PoiCategoryRef>28</PoiCategoryRef>
      <!--Одежда-->

      <!--Органы самоуправлен.-->
      <PoiCategoryRef>46</PoiCategoryRef>
      <!--Отделения связи-->
      <PoiCategoryRef>8</PoiCategoryRef>
      <!--Отели и мотели-->
      <PoiCategoryRef>38</PoiCategoryRef>
      <!--Памятники-->
      <PoiCategoryRef>32</PoiCategoryRef>
      <!--Парки-->
      <PoiCategoryRef>44</PoiCategoryRef>
      <!--Парки культ. и отдыха-->
      <PoiCategoryRef>9</PoiCategoryRef>
      <!--Паромы-->

      <!--Пересечения автомаг.-->
      <PoiCategoryRef>10</PoiCategoryRef>
      <!--Погранпереходы-->
      <PoiCategoryRef>20</PoiCategoryRef>
      <!--Полиция/милиция-->
      <PoiCategoryRef>50</PoiCategoryRef>
      <!--Посольства-->
      <PoiCategoryRef>49</PoiCategoryRef>
      <!--Правит., органы управл.-->
      <PoiCategoryRef>15</PoiCategoryRef>
      <!--Прокат автомобилей-->
      <PoiCategoryRef>24</PoiCategoryRef>
      <!--Рестораны-->
      <PoiCategoryRef>39</PoiCategoryRef>
      <!--Спортивные центры-->

      <!--Спортивный аэродром-->
      <PoiCategoryRef>6</PoiCategoryRef>
      <!--Стоянки-->
      <PoiCategoryRef>14</PoiCategoryRef>
      <!--Съезды/въезды автом.-->
      <PoiCategoryRef>36</PoiCategoryRef>
      <!--Театры, концерт. залы-->
      <PoiCategoryRef>27</PoiCategoryRef>
      <!--Торговые центры-->
      <PoiCategoryRef>7</PoiCategoryRef>
      <!--У автомагистралей-->
      <PoiCategoryRef>47</PoiCategoryRef>
      <!--Фирмы-->
      <PoiCategoryRef>53</PoiCategoryRef>
      <!--Церкви-->
      <PoiCategoryRef>29</PoiCategoryRef>
      <!--Электроника-->
    </PoiCategoryMapping>
    <PoiCategoryMapping fueltype="cng">
      <PoiCategoryRef>1</PoiCategoryRef>
      <!--Autostadt-->
      <PoiCategoryRef>12</PoiCategoryRef>
      <!--SEAT Дилеры-->
      <PoiCategoryRef>11</PoiCategoryRef>
      <!--SEAT Сервисные центры-->
      <PoiCategoryRef>18</PoiCategoryRef>
      <!--Автобусные остановки-->
      <PoiCategoryRef>4</PoiCategoryRef>
      <!--АГЗС (природный газ)-->
      <PoiCategoryRef>3</PoiCategoryRef>
      <!--АГЗС (сжиж. нефт. газ)-->
      <PoiCategoryRef>5</PoiCategoryRef>
      <!--АЗС-->
      <PoiCategoryRef>23</PoiCategoryRef>
      <!--Аптеки-->
      <PoiCategoryRef>2</PoiCategoryRef>
      <!--Аэропорты-->
      <PoiCategoryRef>45</PoiCategoryRef>
      <!--Банки-->
      <PoiCategoryRef>25</PoiCategoryRef>
      <!--Банкоматы-->
      <PoiCategoryRef>21</PoiCategoryRef>
      <!--Больницы-->
      <PoiCategoryRef>30</PoiCategoryRef>
      <!--Вина и крепкие напитки-->
      <PoiCategoryRef>41</PoiCategoryRef>
      <!--Гольф-->
      <PoiCategoryRef>33</PoiCategoryRef>
      <!--Достопримечательн.-->
      <PoiCategoryRef>16</PoiCategoryRef>
      <!--Ж/д вокзалы-->
      <PoiCategoryRef>55</PoiCategoryRef>
      <!--Зарядные станции-->
      <PoiCategoryRef>19</PoiCategoryRef>
      <!--Инф. для туристов-->
      <PoiCategoryRef>35</PoiCategoryRef>
      <!--Казино-->
      <PoiCategoryRef>26</PoiCategoryRef>
      <!--Кафе-->
      <PoiCategoryRef>34</PoiCategoryRef>
      <!--Кинотеатры-->
      <PoiCategoryRef>54</PoiCategoryRef>
      <!--Кладбища-->
      <PoiCategoryRef>48</PoiCategoryRef>
      <!--Конгресс-центры-->
      <PoiCategoryRef>42</PoiCategoryRef>
      <!--Лодочный спорт-->
      <PoiCategoryRef>43</PoiCategoryRef>
      <!--Лыжи-->
      <PoiCategoryRef>22</PoiCategoryRef>
      <!--Медицинск.учреждения-->
      <PoiCategoryRef>37</PoiCategoryRef>
      <!--Музеи-->
      <PoiCategoryRef>31</PoiCategoryRef>
      <!--Ночная жизнь-->
      <PoiCategoryRef>52</PoiCategoryRef>
      <!--Образоват. учреждения-->
      <PoiCategoryRef>28</PoiCategoryRef>
      <!--Одежда-->

      <!--Органы самоуправлен.-->
      <PoiCategoryRef>46</PoiCategoryRef>
      <!--Отделения связи-->
      <PoiCategoryRef>8</PoiCategoryRef>
      <!--Отели и мотели-->
      <PoiCategoryRef>38</PoiCategoryRef>
      <!--Памятники-->
      <PoiCategoryRef>32</PoiCategoryRef>
      <!--Парки-->
      <PoiCategoryRef>44</PoiCategoryRef>
      <!--Парки культ. и отдыха-->
      <PoiCategoryRef>9</PoiCategoryRef>
      <!--Паромы-->

      <!--Пересечения автомаг.-->
      <PoiCategoryRef>10</PoiCategoryRef>
      <!--Погранпереходы-->
      <PoiCategoryRef>20</PoiCategoryRef>
      <!--Полиция/милиция-->
      <PoiCategoryRef>50</PoiCategoryRef>
      <!--Посольства-->
      <PoiCategoryRef>49</PoiCategoryRef>
      <!--Правит., органы управл.-->
      <PoiCategoryRef>15</PoiCategoryRef>
      <!--Прокат автомобилей-->
      <PoiCategoryRef>24</PoiCategoryRef>
      <!--Рестораны-->
      <PoiCategoryRef>39</PoiCategoryRef>
      <!--Спортивные центры-->

      <!--Спортивный аэродром-->
      <PoiCategoryRef>6</PoiCategoryRef>
      <!--Стоянки-->
      <PoiCategoryRef>14</PoiCategoryRef>
      <!--Съезды/въезды автом.-->
      <PoiCategoryRef>36</PoiCategoryRef>
      <!--Театры, концерт. залы-->
      <PoiCategoryRef>27</PoiCategoryRef>
      <!--Торговые центры-->
      <PoiCategoryRef>7</PoiCategoryRef>
      <!--У автомагистралей-->
      <PoiCategoryRef>47</PoiCategoryRef>
      <!--Фирмы-->
      <PoiCategoryRef>53</PoiCategoryRef>
      <!--Церкви-->
      <PoiCategoryRef>29</PoiCategoryRef>
      <!--Электроника-->
    </PoiCategoryMapping>
    <PoiCategoryMapping fueltype="lpg">
      <PoiCategoryRef>1</PoiCategoryRef>
      <!--Autostadt-->
      <PoiCategoryRef>12</PoiCategoryRef>
      <!--SEAT Дилеры-->
      <PoiCategoryRef>11</PoiCategoryRef>
      <!--SEAT Сервисные центры-->
      <PoiCategoryRef>18</PoiCategoryRef>
      <!--Автобусные остановки-->
      <PoiCategoryRef>4</PoiCategoryRef>
      <!--АГЗС (природный газ)-->
      <PoiCategoryRef>3</PoiCategoryRef>
      <!--АГЗС (сжиж. нефт. газ)-->
      <PoiCategoryRef>5</PoiCategoryRef>
      <!--АЗС-->
      <PoiCategoryRef>23</PoiCategoryRef>
      <!--Аптеки-->
      <PoiCategoryRef>2</PoiCategoryRef>
      <!--Аэропорты-->
      <PoiCategoryRef>45</PoiCategoryRef>
      <!--Банки-->
      <PoiCategoryRef>25</PoiCategoryRef>
      <!--Банкоматы-->
      <PoiCategoryRef>21</PoiCategoryRef>
      <!--Больницы-->
      <PoiCategoryRef>30</PoiCategoryRef>
      <!--Вина и крепкие напитки-->
      <PoiCategoryRef>41</PoiCategoryRef>
      <!--Гольф-->
      <PoiCategoryRef>33</PoiCategoryRef>
      <!--Достопримечательн.-->
      <PoiCategoryRef>16</PoiCategoryRef>
      <!--Ж/д вокзалы-->
      <PoiCategoryRef>55</PoiCategoryRef>
      <!--Зарядные станции-->
      <PoiCategoryRef>19</PoiCategoryRef>
      <!--Инф. для туристов-->
      <PoiCategoryRef>35</PoiCategoryRef>
      <!--Казино-->
      <PoiCategoryRef>26</PoiCategoryRef>
      <!--Кафе-->
      <PoiCategoryRef>34</PoiCategoryRef>
      <!--Кинотеатры-->
      <PoiCategoryRef>54</PoiCategoryRef>
      <!--Кладбища-->
      <PoiCategoryRef>48</PoiCategoryRef>
      <!--Конгресс-центры-->
      <PoiCategoryRef>42</PoiCategoryRef>
      <!--Лодочный спорт-->
      <PoiCategoryRef>43</PoiCategoryRef>
      <!--Лыжи-->
      <PoiCategoryRef>22</PoiCategoryRef>
      <!--Медицинск.учреждения-->
      <PoiCategoryRef>37</PoiCategoryRef>
      <!--Музеи-->
      <PoiCategoryRef>31</PoiCategoryRef>
      <!--Ночная жизнь-->
      <PoiCategoryRef>52</PoiCategoryRef>
      <!--Образоват. учреждения-->
      <PoiCategoryRef>28</PoiCategoryRef>
      <!--Одежда-->

      <!--Органы самоуправлен.-->
      <PoiCategoryRef>46</PoiCategoryRef>
      <!--Отделения связи-->
      <PoiCategoryRef>8</PoiCategoryRef>
      <!--Отели и мотели-->
      <PoiCategoryRef>38</PoiCategoryRef>
      <!--Памятники-->
      <PoiCategoryRef>32</PoiCategoryRef>
      <!--Парки-->
      <PoiCategoryRef>44</PoiCategoryRef>
      <!--Парки культ. и отдыха-->
      <PoiCategoryRef>9</PoiCategoryRef>
      <!--Паромы-->

      <!--Пересечения автомаг.-->
      <PoiCategoryRef>10</PoiCategoryRef>
      <!--Погранпереходы-->
      <PoiCategoryRef>20</PoiCategoryRef>
      <!--Полиция/милиция-->
      <PoiCategoryRef>50</PoiCategoryRef>
      <!--Посольства-->
      <PoiCategoryRef>49</PoiCategoryRef>
      <!--Правит., органы управл.-->
      <PoiCategoryRef>15</PoiCategoryRef>
      <!--Прокат автомобилей-->
      <PoiCategoryRef>24</PoiCategoryRef>
      <!--Рестораны-->
      <PoiCategoryRef>39</PoiCategoryRef>
      <!--Спортивные центры-->

      <!--Спортивный аэродром-->
      <PoiCategoryRef>6</PoiCategoryRef>
      <!--Стоянки-->
      <PoiCategoryRef>14</PoiCategoryRef>
      <!--Съезды/въезды автом.-->
      <PoiCategoryRef>36</PoiCategoryRef>
      <!--Театры, концерт. залы-->
      <PoiCategoryRef>27</PoiCategoryRef>
      <!--Торговые центры-->
      <PoiCategoryRef>7</PoiCategoryRef>
      <!--У автомагистралей-->
      <PoiCategoryRef>47</PoiCategoryRef>
      <!--Фирмы-->
      <PoiCategoryRef>53</PoiCategoryRef>
      <!--Церкви-->
      <PoiCategoryRef>29</PoiCategoryRef>
      <!--Электроника-->
    </PoiCategoryMapping>
    <PoiCategoryMapping fueltype="bev">
      <PoiCategoryRef>23</PoiCategoryRef>
      <PoiCategoryRef>1</PoiCategoryRef>
      <!--Autostadt-->
      <PoiCategoryRef>12</PoiCategoryRef>
      <!--SEAT Дилеры-->
      <PoiCategoryRef>11</PoiCategoryRef>
      <!--SEAT Сервисные центры-->
      <PoiCategoryRef>18</PoiCategoryRef>
      <!--Автобусные остановки-->
      <PoiCategoryRef>4</PoiCategoryRef>
      <!--АГЗС (природный газ)-->
      <PoiCategoryRef>3</PoiCategoryRef>
      <!--АГЗС (сжиж. нефт. газ)-->
      <PoiCategoryRef>5</PoiCategoryRef>
      <!--АЗС-->
      <PoiCategoryRef>23</PoiCategoryRef>
      <!--Аптеки-->
      <PoiCategoryRef>2</PoiCategoryRef>
      <!--Аэропорты-->
      <PoiCategoryRef>45</PoiCategoryRef>
      <!--Банки-->
      <PoiCategoryRef>25</PoiCategoryRef>
      <!--Банкоматы-->
      <PoiCategoryRef>21</PoiCategoryRef>
      <!--Больницы-->
      <PoiCategoryRef>30</PoiCategoryRef>
      <!--Вина и крепкие напитки-->
      <PoiCategoryRef>41</PoiCategoryRef>
      <!--Гольф-->
      <PoiCategoryRef>33</PoiCategoryRef>
      <!--Достопримечательн.-->
      <PoiCategoryRef>16</PoiCategoryRef>
      <!--Ж/д вокзалы-->
      <PoiCategoryRef>55</PoiCategoryRef>
      <!--Зарядные станции-->
      <PoiCategoryRef>19</PoiCategoryRef>
      <!--Инф. для туристов-->
      <PoiCategoryRef>35</PoiCategoryRef>
      <!--Казино-->
      <PoiCategoryRef>26</PoiCategoryRef>
      <!--Кафе-->
      <PoiCategoryRef>34</PoiCategoryRef>
      <!--Кинотеатры-->
      <PoiCategoryRef>54</PoiCategoryRef>
      <!--Кладбища-->
      <PoiCategoryRef>48</PoiCategoryRef>
      <!--Конгресс-центры-->
      <PoiCategoryRef>42</PoiCategoryRef>
      <!--Лодочный спорт-->
      <PoiCategoryRef>43</PoiCategoryRef>
      <!--Лыжи-->
      <PoiCategoryRef>22</PoiCategoryRef>
      <!--Медицинск.учреждения-->
      <PoiCategoryRef>37</PoiCategoryRef>
      <!--Музеи-->
      <PoiCategoryRef>31</PoiCategoryRef>
      <!--Ночная жизнь-->
      <PoiCategoryRef>52</PoiCategoryRef>
      <!--Образоват. учреждения-->
      <PoiCategoryRef>28</PoiCategoryRef>
      <!--Одежда-->

      <!--Органы самоуправлен.-->
      <PoiCategoryRef>46</PoiCategoryRef>
      <!--Отделения связи-->
      <PoiCategoryRef>8</PoiCategoryRef>
      <!--Отели и мотели-->
      <PoiCategoryRef>38</PoiCategoryRef>
      <!--Памятники-->
      <PoiCategoryRef>32</PoiCategoryRef>
      <!--Парки-->
      <PoiCategoryRef>44</PoiCategoryRef>
      <!--Парки культ. и отдыха-->
      <PoiCategoryRef>9</PoiCategoryRef>
      <!--Паромы-->

      <!--Пересечения автомаг.-->
      <PoiCategoryRef>10</PoiCategoryRef>
      <!--Погранпереходы-->
      <PoiCategoryRef>20</PoiCategoryRef>
      <!--Полиция/милиция-->
      <PoiCategoryRef>50</PoiCategoryRef>
      <!--Посольства-->
      <PoiCategoryRef>49</PoiCategoryRef>
      <!--Правит., органы управл.-->
      <PoiCategoryRef>15</PoiCategoryRef>
      <!--Прокат автомобилей-->
      <PoiCategoryRef>24</PoiCategoryRef>
      <!--Рестораны-->
      <PoiCategoryRef>39</PoiCategoryRef>
      <!--Спортивные центры-->

      <!--Спортивный аэродром-->
      <PoiCategoryRef>6</PoiCategoryRef>
      <!--Стоянки-->
      <PoiCategoryRef>14</PoiCategoryRef>
      <!--Съезды/въезды автом.-->
      <PoiCategoryRef>36</PoiCategoryRef>
      <!--Театры, концерт. залы-->
      <PoiCategoryRef>27</PoiCategoryRef>
      <!--Торговые центры-->
      <PoiCategoryRef>7</PoiCategoryRef>
      <!--У автомагистралей-->
      <PoiCategoryRef>47</PoiCategoryRef>
      <!--Фирмы-->
      <PoiCategoryRef>53</PoiCategoryRef>
      <!--Церкви-->
      <PoiCategoryRef>29</PoiCategoryRef>
      <!--Электроника-->
    </PoiCategoryMapping>
    <PoiCategoryMapping fueltype="phev">
      <PoiCategoryRef>1</PoiCategoryRef>
      <!--Autostadt-->
      <PoiCategoryRef>12</PoiCategoryRef>
      <!--SEAT Дилеры-->
      <PoiCategoryRef>11</PoiCategoryRef>
      <!--SEAT Сервисные центры-->
      <PoiCategoryRef>18</PoiCategoryRef>
      <!--Автобусные остановки-->
      <PoiCategoryRef>4</PoiCategoryRef>
      <!--АГЗС (природный газ)-->
      <PoiCategoryRef>3</PoiCategoryRef>
      <!--АГЗС (сжиж. нефт. газ)-->
      <PoiCategoryRef>5</PoiCategoryRef>
      <!--АЗС-->
      <PoiCategoryRef>23</PoiCategoryRef>
      <!--Аптеки-->
      <PoiCategoryRef>2</PoiCategoryRef>
      <!--Аэропорты-->
      <PoiCategoryRef>45</PoiCategoryRef>
      <!--Банки-->
      <PoiCategoryRef>25</PoiCategoryRef>
      <!--Банкоматы-->
      <PoiCategoryRef>21</PoiCategoryRef>
      <!--Больницы-->
      <PoiCategoryRef>30</PoiCategoryRef>
      <!--Вина и крепкие напитки-->
      <PoiCategoryRef>41</PoiCategoryRef>
      <!--Гольф-->
      <PoiCategoryRef>33</PoiCategoryRef>
      <!--Достопримечательн.-->
      <PoiCategoryRef>16</PoiCategoryRef>
      <!--Ж/д вокзалы-->
      <PoiCategoryRef>55</PoiCategoryRef>
      <!--Зарядные станции-->
      <PoiCategoryRef>19</PoiCategoryRef>
      <!--Инф. для туристов-->
      <PoiCategoryRef>35</PoiCategoryRef>
      <!--Казино-->
      <PoiCategoryRef>26</PoiCategoryRef>
      <!--Кафе-->
      <PoiCategoryRef>34</PoiCategoryRef>
      <!--Кинотеатры-->
      <PoiCategoryRef>54</PoiCategoryRef>
      <!--Кладбища-->
      <PoiCategoryRef>48</PoiCategoryRef>
      <!--Конгресс-центры-->
      <PoiCategoryRef>42</PoiCategoryRef>
      <!--Лодочный спорт-->
      <PoiCategoryRef>43</PoiCategoryRef>
      <!--Лыжи-->
      <PoiCategoryRef>22</PoiCategoryRef>
      <!--Медицинск.учреждения-->
      <PoiCategoryRef>37</PoiCategoryRef>
      <!--Музеи-->
      <PoiCategoryRef>31</PoiCategoryRef>
      <!--Ночная жизнь-->
      <PoiCategoryRef>52</PoiCategoryRef>
      <!--Образоват. учреждения-->
      <PoiCategoryRef>28</PoiCategoryRef>
      <!--Одежда-->

      <!--Органы самоуправлен.-->
      <PoiCategoryRef>46</PoiCategoryRef>
      <!--Отделения связи-->
      <PoiCategoryRef>8</PoiCategoryRef>
      <!--Отели и мотели-->
      <PoiCategoryRef>38</PoiCategoryRef>
      <!--Памятники-->
      <PoiCategoryRef>32</PoiCategoryRef>
      <!--Парки-->
      <PoiCategoryRef>44</PoiCategoryRef>
      <!--Парки культ. и отдыха-->
      <PoiCategoryRef>9</PoiCategoryRef>
      <!--Паромы-->

      <!--Пересечения автомаг.-->
      <PoiCategoryRef>10</PoiCategoryRef>
      <!--Погранпереходы-->
      <PoiCategoryRef>20</PoiCategoryRef>
      <!--Полиция/милиция-->
      <PoiCategoryRef>50</PoiCategoryRef>
      <!--Посольства-->
      <PoiCategoryRef>49</PoiCategoryRef>
      <!--Правит., органы управл.-->
      <PoiCategoryRef>15</PoiCategoryRef>
      <!--Прокат автомобилей-->
      <PoiCategoryRef>24</PoiCategoryRef>
      <!--Рестораны-->
      <PoiCategoryRef>39</PoiCategoryRef>
      <!--Спортивные центры-->

      <!--Спортивный аэродром-->
      <PoiCategoryRef>6</PoiCategoryRef>
      <!--Стоянки-->
      <PoiCategoryRef>14</PoiCategoryRef>
      <!--Съезды/въезды автом.-->
      <PoiCategoryRef>36</PoiCategoryRef>
      <!--Театры, концерт. залы-->
      <PoiCategoryRef>27</PoiCategoryRef>
      <!--Торговые центры-->
      <PoiCategoryRef>7</PoiCategoryRef>
      <!--У автомагистралей-->
      <PoiCategoryRef>47</PoiCategoryRef>
      <!--Фирмы-->
      <PoiCategoryRef>53</PoiCategoryRef>
      <!--Церкви-->
      <PoiCategoryRef>29</PoiCategoryRef>
      <!--Электроника-->
    </PoiCategoryMapping>
  </SetupCategoryDefinition>

  <!-- ### Poi category groups defined by vw, the type defines the "local" or "personal Poi" or other types -->
  <PoiCategoryGroupDefinition>
    <PoiCategoryGroup id="10" type="dynamic">
      <Priority>1</Priority>
      <PoiCategoryMapping>
        <!-- MUSS LEER BLEIBEN Ueber XSD checken !! -->
      </PoiCategoryMapping>
    </PoiCategoryGroup>

    <PoiCategoryGroup id="11" type="local">
      <Priority>2</Priority>
      <PoiCategoryMapping>
        <PoiCategoryRef>1</PoiCategoryRef>
        <!-- Autostadt -->
        <PoiCategoryRef>12</PoiCategoryRef>
        <!-- SEAT Дилеры -->
        <PoiCategoryRef>11</PoiCategoryRef>
        <!-- SEAT Сервисные центры -->
        <PoiCategoryRef>18</PoiCategoryRef>
        <!-- Автобусные остановки -->
        <PoiCategoryRef>4</PoiCategoryRef>
        <!-- АГЗС (природный газ) -->
        <PoiCategoryRef>3</PoiCategoryRef>
        <!-- АГЗС (сжиж. нефт. газ) -->
        <PoiCategoryRef>5</PoiCategoryRef>
        <!-- АЗС -->
        <PoiCategoryRef>23</PoiCategoryRef>
        <!-- Аптеки -->
        <PoiCategoryRef>2</PoiCategoryRef>
        <!-- Аэропорты -->
        <PoiCategoryRef>45</PoiCategoryRef>
        <!-- Банки -->
        <PoiCategoryRef>25</PoiCategoryRef>
        <!-- Банкоматы -->
        <PoiCategoryRef>21</PoiCategoryRef>
        <!-- Больницы -->
        <PoiCategoryRef>30</PoiCategoryRef>
        <!-- Вина и крепкие напитки -->
        <PoiCategoryRef>41</PoiCategoryRef>
        <!-- Гольф -->
        <PoiCategoryRef>33</PoiCategoryRef>
        <!-- Достопримечательн. -->
        <PoiCategoryRef>16</PoiCategoryRef>
        <!-- Ж/д вокзалы -->
        <PoiCategoryRef>55</PoiCategoryRef>
        <!-- Зарядные станции -->
        <PoiCategoryRef>19</PoiCategoryRef>
        <!-- Инф. для туристов -->
        <PoiCategoryRef>35</PoiCategoryRef>
        <!-- Казино -->
        <PoiCategoryRef>26</PoiCategoryRef>
        <!-- Кафе -->
        <PoiCategoryRef>34</PoiCategoryRef>
        <!-- Кинотеатры -->
        <PoiCategoryRef>54</PoiCategoryRef>
        <!-- Кладбища -->
        <PoiCategoryRef>48</PoiCategoryRef>
        <!-- Конгресс-центры -->
        <PoiCategoryRef>42</PoiCategoryRef>
        <!-- Лодочный спорт -->
        <PoiCategoryRef>43</PoiCategoryRef>
        <!-- Лыжи -->
        <PoiCategoryRef>22</PoiCategoryRef>
        <!-- Медицинск.учреждения -->
        <PoiCategoryRef>37</PoiCategoryRef>
        <!-- Музеи -->
        <PoiCategoryRef>31</PoiCategoryRef>
        <!-- Ночная жизнь -->
        <PoiCategoryRef>52</PoiCategoryRef>
        <!-- Образоват. учреждения -->
        <PoiCategoryRef>28</PoiCategoryRef>
        <!-- Одежда -->

        <!-- Органы самоуправлен. -->
        <PoiCategoryRef>46</PoiCategoryRef>
        <!-- Отделения связи -->
        <PoiCategoryRef>8</PoiCategoryRef>
        <!-- Отели и мотели -->
        <PoiCategoryRef>38</PoiCategoryRef>
        <!-- Памятники -->
        <PoiCategoryRef>32</PoiCategoryRef>
        <!-- Парки -->
        <PoiCategoryRef>44</PoiCategoryRef>
        <!-- Парки культ. и отдыха -->
        <PoiCategoryRef>9</PoiCategoryRef>
        <!-- Паромы -->

        <!-- Пересечения автомаг. -->
        <PoiCategoryRef>10</PoiCategoryRef>
        <!-- Погранпереходы -->
        <PoiCategoryRef>20</PoiCategoryRef>
        <!-- Полиция/милиция -->
        <PoiCategoryRef>50</PoiCategoryRef>
        <!-- Посольства -->
        <PoiCategoryRef>49</PoiCategoryRef>
        <!-- Правит., органы управл. -->
        <PoiCategoryRef>15</PoiCategoryRef>
        <!-- Прокат автомобилей -->
        <PoiCategoryRef>24</PoiCategoryRef>
        <!-- Рестораны -->
        <PoiCategoryRef>39</PoiCategoryRef>
        <!-- Спортивные центры -->

        <!-- Спортивный аэродром -->
        <PoiCategoryRef>6</PoiCategoryRef>
        <!-- Стоянки -->
        <PoiCategoryRef>14</PoiCategoryRef>
        <!-- Съезды/въезды автом. -->
        <PoiCategoryRef>36</PoiCategoryRef>
        <!-- Театры, концерт. залы -->
        <PoiCategoryRef>27</PoiCategoryRef>
        <!-- Торговые центры -->
        <PoiCategoryRef>7</PoiCategoryRef>
        <!-- У автомагистралей -->
        <PoiCategoryRef>47</PoiCategoryRef>
        <!-- Фирмы -->
        <PoiCategoryRef>53</PoiCategoryRef>
        <!-- Церкви -->
        <PoiCategoryRef>29</PoiCategoryRef>
        <!-- Электроника -->
      </PoiCategoryMapping>
    </PoiCategoryGroup>

    <PoiCategoryGroup id="12" type="local">
      <Priority>3</Priority>
      <PoiCategoryMapping>
        <PoiCategoryRef>12</PoiCategoryRef>
        <!-- SEAT Дилеры -->
        <PoiCategoryRef>11</PoiCategoryRef>
        <!-- SEAT Сервисные центры -->
        <PoiCategoryRef>18</PoiCategoryRef>
        <!-- Автобусные остановки -->
        <PoiCategoryRef>4</PoiCategoryRef>
        <!-- АГЗС (природный газ) -->
        <PoiCategoryRef>3</PoiCategoryRef>
        <!-- АГЗС (сжиж. нефт. газ) -->
        <PoiCategoryRef>5</PoiCategoryRef>
        <!-- АЗС -->
        <PoiCategoryRef>2</PoiCategoryRef>
        <!-- Аэропорты -->
        <PoiCategoryRef>16</PoiCategoryRef>
        <!-- Ж/д вокзалы -->
        <PoiCategoryRef>55</PoiCategoryRef>
        <!-- Зарядные станции -->
        <PoiCategoryRef>19</PoiCategoryRef>
        <!-- Инф. для туристов -->
        <PoiCategoryRef>8</PoiCategoryRef>
        <!-- Отели и мотели -->
        <PoiCategoryRef>9</PoiCategoryRef>
        <!-- Паромы -->

        <!-- Пересечения автомаг. -->
        <PoiCategoryRef>10</PoiCategoryRef>
        <!-- Погранпереходы -->
        <PoiCategoryRef>15</PoiCategoryRef>
        <!-- Прокат автомобилей -->
        <PoiCategoryRef>6</PoiCategoryRef>
        <!-- Стоянки -->
        <PoiCategoryRef>14</PoiCategoryRef>
        <!-- Съезды/въезды автом. -->
        <PoiCategoryRef>7</PoiCategoryRef>
        <!-- У автомагистралей -->
      </PoiCategoryMapping>
    </PoiCategoryGroup>

    <PoiCategoryGroup id="13" type="local">
      <Priority>4</Priority>
      <PoiCategoryMapping>
        <PoiCategoryRef>1</PoiCategoryRef>
        <!-- Autostadt -->
        <PoiCategoryRef>41</PoiCategoryRef>
        <!-- Гольф -->
        <PoiCategoryRef>33</PoiCategoryRef>
        <!-- Достопримечательн. -->
        <PoiCategoryRef>35</PoiCategoryRef>
        <!-- Казино -->
        <PoiCategoryRef>34</PoiCategoryRef>
        <!-- Кинотеатры -->
        <PoiCategoryRef>42</PoiCategoryRef>
        <!-- Лодочный спорт -->
        <PoiCategoryRef>43</PoiCategoryRef>
        <!-- Лыжи -->
        <PoiCategoryRef>37</PoiCategoryRef>
        <!-- Музеи -->
        <PoiCategoryRef>38</PoiCategoryRef>
        <!-- Памятники -->
        <PoiCategoryRef>32</PoiCategoryRef>
        <!-- Парки -->
        <PoiCategoryRef>44</PoiCategoryRef>
        <!-- Парки культ. и отдыха -->
        <PoiCategoryRef>39</PoiCategoryRef>
        <!-- Спортивные центры -->

        <!-- Спортивный аэродром -->
        <PoiCategoryRef>36</PoiCategoryRef>
        <!-- Театры, концерт. залы -->
      </PoiCategoryMapping>
    </PoiCategoryGroup>

    <PoiCategoryGroup id="14" type="local">
      <Priority>5</Priority>
      <PoiCategoryMapping>
        <PoiCategoryRef>25</PoiCategoryRef>
        <!-- Банкоматы -->
        <PoiCategoryRef>30</PoiCategoryRef>
        <!-- Вина и крепкие напитки -->
        <PoiCategoryRef>26</PoiCategoryRef>
        <!-- Кафе -->
        <PoiCategoryRef>31</PoiCategoryRef>
        <!-- Ночная жизнь -->
        <PoiCategoryRef>28</PoiCategoryRef>
        <!-- Одежда -->
        <PoiCategoryRef>24</PoiCategoryRef>
        <!-- Рестораны -->
        <PoiCategoryRef>27</PoiCategoryRef>
        <!-- Торговые центры -->
        <PoiCategoryRef>29</PoiCategoryRef>
        <!-- Электроника -->
      </PoiCategoryMapping>
    </PoiCategoryGroup>

    <PoiCategoryGroup id="15" type="local">
      <Priority>6</Priority>
      <PoiCategoryMapping>
        <PoiCategoryRef>23</PoiCategoryRef>
        <!-- Аптеки -->
        <PoiCategoryRef>21</PoiCategoryRef>
        <!-- Больницы -->
        <PoiCategoryRef>22</PoiCategoryRef>
        <!-- Медицинск.учреждения -->
        <PoiCategoryRef>20</PoiCategoryRef>
        <!-- Полиция/милиция -->
      </PoiCategoryMapping>
    </PoiCategoryGroup>

    <PoiCategoryGroup id="16" type="local">
      <Priority>7</Priority>
      <PoiCategoryMapping>
        <PoiCategoryRef>45</PoiCategoryRef>
        <!-- Банки -->
        <PoiCategoryRef>54</PoiCategoryRef>
        <!-- Кладбища -->
        <PoiCategoryRef>48</PoiCategoryRef>
        <!-- Конгресс-центры -->
        <PoiCategoryRef>52</PoiCategoryRef>
        <!-- Образоват. учреждения -->

        <!-- Органы самоуправлен. -->
        <PoiCategoryRef>46</PoiCategoryRef>
        <!-- Отделения связи -->
        <PoiCategoryRef>50</PoiCategoryRef>
        <!-- Посольства -->
        <PoiCategoryRef>49</PoiCategoryRef>
        <!-- Правит., органы управл. -->
        <PoiCategoryRef>47</PoiCategoryRef>
        <!-- Фирмы -->
        <PoiCategoryRef>53</PoiCategoryRef>
        <!-- Церкви -->
      </PoiCategoryMapping>
    </PoiCategoryGroup>

  </PoiCategoryGroupDefinition>

  <PoiCategoryGroupNameDefinition>
    <Name category_group_ref="10">Мои объекты (персональные объекты)</Name>
    <Name category_group_ref="11">Категор. (по алфавиту)</Name>
    <Name category_group_ref="16">Фирмы и учреждения</Name>
    <Name category_group_ref="15">Если что-то случилось</Name>
    <Name category_group_ref="13">Достопр., места отдыха</Name>
    <Name category_group_ref="12">А/м и путешествия</Name>
    <Name category_group_ref="14">Еда и покупки</Name>
  </PoiCategoryGroupNameDefinition>

  <PoiCategoryThesaurusDefinition>
    <Thesaurus category_ref="1" >
      <Value>Autostadt</Value>
    </Thesaurus>
    <Thesaurus category_ref="2" >
      <Value>АЭРОДРОМ</Value>
      <Value>ОТЛЁТ</Value>
      <Value>ПРИЛЁТ</Value>
      <Value>ТЕРМИНАЛ</Value>
      <Value>ПУТЕШЕСТВОВАТЬ</Value>
      <Value>САМОЛЁТ</Value>
      <Value>ПОЛЁТ</Value>
      <Value>АЭРОПОРТ</Value>
    </Thesaurus>
    <Thesaurus category_ref="3" >
      <Value>LPG</Value>
      <Value>газ</Value>
      <Value>заправиться</Value>
      <Value>заправка</Value>
      <Value>АГЗС</Value>
      <Value>автозаправка</Value>
      <Value>пропан-бутан</Value>
      <Value>сжиженный газ</Value>
    </Thesaurus>
    <Thesaurus category_ref="4" >
      <Value>ЗАПРАВКА</Value>
      <Value>АГЗС</Value>
      <Value>ЗАПРАВИТЬСЯ</Value>
      <Value>АВТОЗАПРАВКА</Value>
      <Value>МЕТАН</Value>
      <Value>АЗС ДЛЯ АВТОМОБИЛЕЙ НА ПРИРОДНОМ ГАЗЕ</Value>
      <Value>ПРИРОДНЫЙ ГАЗ</Value>
      <Value>CNG</Value>
    </Thesaurus>
    <Thesaurus category_ref="5" >
      <Value>бензин</Value>
      <Value>дизель</Value>
      <Value>заправиться</Value>
      <Value>заправка</Value>
      <Value>горючее</Value>
      <Value>солярка</Value>
      <Value>дизтопливо</Value>
      <Value>топливо</Value>
      <Value>азс</Value>
    </Thesaurus>
    <Thesaurus category_ref="6" >
      <Value>парковка</Value>
      <Value>гараж</Value>
      <Value>автостоянка</Value>
      <Value>стоянка</Value>
      <Value>паркинг</Value>
    </Thesaurus>
    <Thesaurus category_ref="7" >
      <Value>спать</Value>
      <Value>остановка</Value>
      <Value>перекур</Value>
      <Value>отдых</Value>
      <Value>сортир</Value>
      <Value>туалет</Value>
      <Value>есть</Value>
      <Value>кушать</Value>
      <Value>место отдыха у автомагистрали</Value>
    </Thesaurus>
    <Thesaurus category_ref="8" >
      <Value>ОТЕЛЬ</Value>
      <Value>МОТЕЛЬ</Value>
      <Value>СПАТЬ</Value>
      <Value>ПАНСИОН</Value>
      <Value>ГОСТИНИЦА</Value>
      <Value>РАЗМЕЩЕНИЕ</Value>
      <Value>НОМЕРА</Value>
      <Value>НОЧЛЕГ</Value>
      <Value>НОЧЁВКА</Value>
    </Thesaurus>
    <Thesaurus category_ref="9" >
      <Value>ПОРТ</Value>
      <Value>ПЕРЕПРАВА</Value>
      <Value>ПАРОМ</Value>
      <Value>СУДНО</Value>
      <Value>КОРАБЛЬ</Value>
      <Value>ГАВАНЬ</Value>
    </Thesaurus>
    <Thesaurus category_ref="10">
      <Value>ПОГРАНПЕРЕХОД</Value>
      <Value>ПЕРЕХОД</Value>
      <Value>ГРАНИЦА</Value>
    </Thesaurus>
    <Thesaurus category_ref="11">
      <Value>продажа автомобилей</Value>
      <Value>продажа аксессуаров</Value>
      <Value>автомобили</Value>
      <Value>аксессуары</Value>
      <Value>дилер</Value>
      <Value>дилерское предприятие</Value>
      <Value>SEAT</Value>
      <Value>Passat</Value>
    </Thesaurus>
    <Thesaurus category_ref="12">
      <Value>SEAT</Value>
      <Value>сервис</Value>
      <Value>ремонт</Value>
      <Value>сто</Value>
      <Value>обслуживание</Value>
      <Value>то</Value>
      <Value>дилер</Value>
      <Value>сервис-центр</Value>
      <Value>сервисный центр</Value>
    </Thesaurus>
    <!--<Thesaurus category_ref="13">
      <Value>СЪЕЗД</Value>
      <Value>ПЕРЕСЕЧЕНИЕ</Value>
      <Value>ПЕРЕКРЁСТОК</Value>
      <Value>РАЗВЯЗКА</Value>
      <Value>ПРИМЫКАНИЕ</Value>
      <Value>ВЫЕЗД</Value>
      <Value>СЪЕЗД С АВТОМАГИСТРАЛИ</Value>
    </Thesaurus>-->
    <Thesaurus category_ref="14">
      <Value>СЪЕЗД</Value>
      <Value>ПЕРЕСЕЧЕНИЕ</Value>
      <Value>ПЕРЕКРЁСТОК</Value>
      <Value>РАЗВЯЗКА</Value>
      <Value>ПРИМЫКАНИЕ</Value>
      <Value>ВЫЕЗД</Value>
      <Value>СЪЕЗД С АВТОМАГИСТРАЛИ</Value>
    </Thesaurus>
    <Thesaurus category_ref="15">
      <Value>ПРОКАТ</Value>
      <Value>АВТОПРОКАТ</Value>
      <Value>АВТОМОБИЛИ</Value>
      <Value>АРЕНДА</Value>
      <Value>МАШИНЫ</Value>
      <Value>ТАЧКИ</Value>
      <Value>ПРОКАТ АВТОМОБИЛЕЙ</Value>
    </Thesaurus>
    <Thesaurus category_ref="16">
      <Value>ПОЕЗД</Value>
      <Value>ПУТЕШЕСТВИЕ</Value>
      <Value>ЖЕЛДОР</Value>
      <Value>ОСТАНОВКА</Value>
      <Value>ЭЛЕКТРИЧКА</Value>
      <Value>ПАРОВОЗ</Value>
      <Value>СТАНЦИЯ</Value>
      <Value>ВОКЗАЛ</Value>
    </Thesaurus>
    <!--<Thesaurus category_ref="17">
      <Value>транспорт</Value>
      <Value>электричка</Value>
      <Value>трамвай</Value>
      <Value>местный транспорт</Value>
    </Thesaurus>-->
    <Thesaurus category_ref="18">
      <Value>автобус</Value>
      <Value>троллейбус</Value>
      <Value>автобусная остановка</Value>
      <Value>остановка</Value>
      <Value>остановка автобусов</Value>
      <Value>остановка троллейбусов</Value>
    </Thesaurus>
    <Thesaurus category_ref="19">
      <Value>турист</Value>
      <Value>справка</Value>
      <Value>информация</Value>
      <Value>турбюро</Value>
      <Value>достопримечательности</Value>
      <Value>интересные места</Value>
    </Thesaurus>
    <Thesaurus category_ref="20">
      <Value>помощь</Value>
      <Value>нападение</Value>
      <Value>разбой</Value>
      <Value>грабёж</Value>
      <Value>хищение</Value>
      <Value>полиция</Value>
      <Value>милиция</Value>
      <Value>менты</Value>
      <Value>донести</Value>
      <Value>настучать</Value>
      <Value>уведомить</Value>
      <Value>02</Value>
      <Value>112</Value>
    </Thesaurus>
    <Thesaurus category_ref="21">
      <Value>ГОСПИТАЛЬ</Value>
      <Value>ПОЛИКЛИНИКА</Value>
      <Value>КЛИНИКА</Value>
      <Value>СТАЦИОНАР</Value>
      <Value>ВРАЧ</Value>
      <Value>АВАРИЯ</Value>
      <Value>ПОМОЩЬ</Value>
      <Value>ГОСПИТАЛИЗАЦИЯ</Value>
      <Value>БОЛЬНИЦА</Value>
    </Thesaurus>
    <Thesaurus category_ref="22">
      <Value>врач</Value>
      <Value>частная практика</Value>
      <Value>здоровье</Value>
      <Value>медслужба</Value>
    </Thesaurus>
    <Thesaurus category_ref="23">
      <Value>медикаменты</Value>
      <Value>лекарства</Value>
      <Value>медицина</Value>
      <Value>рецепт</Value>
      <Value>аптека</Value>
      <Value>аспирин</Value>
      <Value>боль</Value>
      <Value>таблетки</Value>
      <Value>аптеки</Value>
    </Thesaurus>
    <Thesaurus category_ref="24">
      <Value>ЕСТЬ</Value>
      <Value>ПИТЬ</Value>
      <Value>ЗАВТРАК</Value>
      <Value>ОБЕД</Value>
      <Value>УЖИН</Value>
      <Value>ТРАКТИР</Value>
      <Value>КАФЕ</Value>
      <Value>БАР</Value>
      <Value>ХАРЧЕВНЯ</Value>
      <Value>ЗАБЕГАЛОВКА</Value>
      <Value>БИСТРО</Value>
      <Value>ЗАКУСОЧНАЯ</Value>
      <Value>КОРЧМА</Value>
      <Value>РЕСТОРАН</Value>
    </Thesaurus>
    <Thesaurus category_ref="25">
      <Value>банкомат</Value>
      <Value>наличные</Value>
      <Value>лавандос</Value>
      <Value>бабло</Value>
      <Value>ловэ</Value>
      <Value>бабки</Value>
      <Value>капуста</Value>
      <Value>кэш</Value>
      <Value>деньги</Value>
      <Value>кредитка</Value>
      <Value>карточка</Value>
      <Value>евро</Value>
      <Value>доллар</Value>
      <Value>рубль</Value>
      <Value>Visa</Value>
      <Value>Mastercard</Value>
    </Thesaurus>
    <Thesaurus category_ref="26">
      <Value>кафе</Value>
      <Value>торт</Value>
      <Value>латте</Value>
      <Value>капучино</Value>
      <Value>эспрессо</Value>
      <Value>кекс</Value>
      <Value>мороженое</Value>
      <Value>гляссе</Value>
      <Value>мокачино</Value>
      <Value>горячий шоколад</Value>
    </Thesaurus>
    <Thesaurus category_ref="27">
      <Value>СУПЕРМАРКЕТ</Value>
      <Value>ПОКУПКИ</Value>
      <Value>ПОКУПАТЬ</Value>
      <Value>УНИВЕРСАМ</Value>
      <Value>ШОПИНГ</Value>
      <Value>ГИПЕРМАРКЕТ</Value>
      <Value>МОЛЛ</Value>
      <Value>МАГАЗИН</Value>
      <Value>ТОРГОВЫЙ ЦЕНТР</Value>
    </Thesaurus>
    <Thesaurus category_ref="28">
      <Value>одежда</Value>
      <Value>шмотки</Value>
      <Value>шмотьё</Value>
      <Value>тряпки</Value>
      <Value>прикид</Value>
      <Value>обувь</Value>
      <Value>шузы</Value>
      <Value>ботинки</Value>
      <Value>сапоги</Value>
      <Value>штаны</Value>
      <Value>брюки</Value>
      <Value>портки</Value>
      <Value>костюм</Value>
    </Thesaurus>
    <Thesaurus category_ref="29">
      <Value>ноутбук</Value>
      <Value>железо</Value>
      <Value>электроника</Value>
      <Value>компьютер</Value>
      <Value>периферия</Value>
      <Value>телевизор</Value>
      <Value>ресиверHiFi</Value>
      <Value>DVD</Value>
      <Value>HiEnd</Value>
      <Value>телефон</Value>
      <Value>мобильник</Value>
      <Value>мобильный телефон</Value>
    </Thesaurus>
    <Thesaurus category_ref="30">
      <Value>ВИНОДЕЛИЕ</Value>
      <Value>ВИНО</Value>
      <Value>ВИННЫЙ</Value>
      <Value>ВИНОТЕКА</Value>
    </Thesaurus>
    <Thesaurus category_ref="31">
      <Value>музыка</Value>
      <Value>дискотека</Value>
      <Value>пати</Value>
      <Value>тусовка</Value>
      <Value>бар</Value>
      <Value>танцевать</Value>
      <Value>коктейль</Value>
      <Value>пивная</Value>
      <Value>паб</Value>
      <Value>пивной ресторан</Value>
    </Thesaurus>
    <Thesaurus category_ref="32">
      <Value>гулять</Value>
      <Value>бегать трусцой</Value>
      <Value>расслабление</Value>
      <Value>пикник</Value>
      <Value>лавочки</Value>
      <Value>аллеи</Value>
      <Value>гулять с собакой</Value>
    </Thesaurus>
    <Thesaurus category_ref="33">
      <Value>ИНФОРМАЦИЯ</Value>
      <Value>ТУРИСТ</Value>
      <Value>СПРАВКА</Value>
      <Value>СПРАВОЧНОЕ БЮРО</Value>
      <Value>ИНФОРМАЦИЯ ДЛЯ ТУРИСТОВ</Value>
    </Thesaurus>
    <Thesaurus category_ref="34">
      <Value>ФИЛЬМ</Value>
      <Value>КИНОФИЛЬМ</Value>
      <Value>КИНОТЕАТР</Value>
      <Value>КИНОШКА</Value>
    </Thesaurus>
    <Thesaurus category_ref="35">
      <Value>игра</Value>
      <Value>играть</Value>
      <Value>игровой автомат</Value>
      <Value>однорукий бандит</Value>
      <Value>рулетка</Value>
      <Value>казино</Value>
      <Value>блек-джек</Value>
      <Value>покер</Value>
      <Value>жетон</Value>
      <Value>игорный дом</Value>
      <Value>джекпот</Value>
    </Thesaurus>
    <Thesaurus category_ref="36">
      <Value>театр</Value>
      <Value>опера</Value>
      <Value>концерт</Value>
      <Value>сцена</Value>
      <Value>подмостки</Value>
      <Value>спектакль</Value>
      <Value>пьеса</Value>
      <Value>драма</Value>
      <Value>мюзикл</Value>
      <Value>искусство</Value>
      <Value>культура</Value>
      <Value>сценическое искусство</Value>
    </Thesaurus>
    <Thesaurus category_ref="37">
      <Value>КУЛЬТУРА</Value>
      <Value>ВЫСТАВКА</Value>
      <Value>ГАЛЕРЕЯ</Value>
      <Value>ИСКУССТВО</Value>
      <Value>ЭКСПОНАТЫ</Value>
      <Value>ЭКСПОЗИЦИЯ</Value>
      <Value>МУЗЕЙ</Value>
    </Thesaurus>
    <Thesaurus category_ref="38">
      <Value>памятник человеку</Value>
      <Value>памятник событию</Value>
      <Value>памятный камень</Value>
      <Value>статуя</Value>
      <Value>монумент</Value>
      <Value>памятник</Value>
    </Thesaurus>
    <Thesaurus category_ref="39">
      <Value>СПОРТ</Value>
      <Value>СТАДИОН</Value>
      <Value>АРЕНА</Value>
      <Value>СПОРТКОМПЛЕКС</Value>
      <Value>СПОРТИВНЫЕ СООРУЖЕНИЯ</Value>
    </Thesaurus>
    <!--<Thesaurus category_ref="40">
      <Value>круговой полёт</Value>
      <Value>полёт на планёре</Value>
      <Value>парение</Value>
      <Value>спортивный аэродром</Value>
      <Value>спортивные аэродромы</Value>
      <Value>полёт</Value>
    </Thesaurus>-->
    <Thesaurus category_ref="41">
      <Value>СПОРТ</Value>
      <Value>ГОЛЬФ</Value>
      <Value>ПОЛЕ ДЛЯ ГОЛЬФА</Value>
    </Thesaurus>
    <Thesaurus category_ref="42">
      <Value>лодка</Value>
      <Value>яхта</Value>
      <Value>море</Value>
      <Value>парус</Value>
      <Value>парусный спорт</Value>
      <Value>порт</Value>
      <Value>лодочный спорт</Value>
      <Value>судно</Value>
      <Value>корабль</Value>
    </Thesaurus>
    <Thesaurus category_ref="43">
      <Value>зима</Value>
      <Value>лыжи</Value>
      <Value>лыжня</Value>
      <Value>подъёмник</Value>
      <Value>снег</Value>
      <Value>лыжный спорт</Value>
      <Value>лыжные гонки</Value>
      <Value>кататься с горки</Value>
      <Value>бобслей</Value>
      <Value>спорт</Value>
    </Thesaurus>
    <Thesaurus category_ref="44">
      <Value>ПАРК ОТДЫХА</Value>
      <Value>РАЗВЛЕЧЕНИЯ</Value>
      <Value>ПАРК</Value>
      <Value>РАЗВЛЕКУХА</Value>
      <Value>ПАРК КУЛЬТУРЫ</Value>
      <Value>КАРУСЕЛЬ</Value>
      <Value>АМЕРИКАНСКИЕ ГОРКИ</Value>
      <Value>КАЧЕЛИ</Value>
      <Value>АТТРАКЦИОНЫ</Value>
    </Thesaurus>
    <Thesaurus category_ref="45">
      <Value>деньги</Value>
      <Value>перевод</Value>
      <Value>счёт</Value>
      <Value>выписка</Value>
      <Value>банки</Value>
      <Value>лавандос</Value>
      <Value>бабло</Value>
      <Value>ловэ</Value>
      <Value>бабки</Value>
      <Value>капуста</Value>
      <Value>монеты</Value>
      <Value>кредит</Value>
    </Thesaurus>
    <Thesaurus category_ref="46">
      <Value>письмо</Value>
      <Value>пакет</Value>
      <Value>деньги</Value>
      <Value>бандероль</Value>
      <Value>посылка</Value>
      <Value>почта</Value>
      <Value>телеграмма</Value>
      <Value>коробка</Value>
    </Thesaurus>
    <Thesaurus category_ref="47">
      <Value>предприятие</Value>
      <Value>завод</Value>
      <Value>компания</Value>
      <Value>фабрика</Value>
      <Value>концерн</Value>
    </Thesaurus>
    <Thesaurus category_ref="48">
      <Value>КОНГРЕСС</Value>
      <Value>ВЫСТАВКА</Value>
      <Value>КОНГРЕССЦЕНТР</Value>
      <Value>ЭКСПО</Value>
      <Value>ЭКСПОЦЕНТР</Value>
      <Value>ЯРМАРКА</Value>
    </Thesaurus>
    <Thesaurus category_ref="49">
      <Value>ВЛАСТЬ</Value>
      <Value>МЭРИЯ</Value>
      <Value>ГОРОД</Value>
      <Value>ОКРУГ</Value>
      <Value>ПРАВИТЕЛЬСТВО</Value>
      <Value>АДМИНИСТРАЦИЯ</Value>
      <Value>РАЗРЕШЕНИЕ</Value>
      <Value>УЧРЕЖДЕНИЕ</Value>
      <Value>ВЕДОМСТВО</Value>
      <Value>ОРГАНЫ ВЛАСТИ</Value>
    </Thesaurus>
    <Thesaurus category_ref="50">
      <Value>консульство</Value>
      <Value>виза</Value>
      <Value>выезд за границу</Value>
      <Value>заграница</Value>
      <Value>посольство</Value>
    </Thesaurus>
    <!--<Thesaurus category_ref="51">
      <Value>ратуша</Value>
      <Value>горсовет</Value>
      <Value>мэрия</Value>
      <Value>исполком</Value>
    </Thesaurus>-->
    <Thesaurus category_ref="52">
      <Value>институт</Value>
      <Value>лицей</Value>
      <Value>гимназия</Value>
      <Value>школа</Value>
      <Value>университет</Value>
      <Value>высшая школа</Value>
      <Value>коледж</Value>
      <Value>ПТУ</Value>
      <Value>путяга</Value>
      <Value>повышение квалификации</Value>
      <Value>семинар</Value>
      <Value>обучение</Value>
    </Thesaurus>
    <Thesaurus category_ref="53">
      <Value>мечеть</Value>
      <Value>собор</Value>
      <Value>синагога</Value>
      <Value>часовня</Value>
      <Value>монастырь</Value>
      <Value>намаз</Value>
      <Value>молитва</Value>
      <Value>храм</Value>
      <Value>церковь</Value>
    </Thesaurus>
    <Thesaurus category_ref="54">
      <Value>погост</Value>
      <Value>могилы</Value>
      <Value>похороны</Value>
      <Value>кладбище</Value>
      <Value>погребение</Value>
      <Value>ритуал</Value>
    </Thesaurus>
    <Thesaurus category_ref="55">
      <Value>зарядная станция</Value>
      <Value>зарядить</Value>
      <Value>зарядка</Value>
      <Value>розетка</Value>
      <Value>розетки</Value>
      <Value>вилка</Value>
      <Value>ток</Value>
      <Value>электричество</Value>
      <Value>сеть зарядных станций</Value>
      <Value>переменное напряжение</Value>
      <Value>постоянное напряжение</Value>
      <Value>зарядная колонка</Value>
    </Thesaurus>
  </PoiCategoryThesaurusDefinition>

  <PoiCategoryNameDefinition>
    <Name category_ref="1" >Autostadt</Name>
    <Name category_ref="2" >Аэропорты</Name>
    <Name category_ref="3" >АГЗС (сжиж. нефт. газ)</Name>
    <Name category_ref="4" >АГЗС (природный газ)</Name>
    <Name category_ref="5" >АЗС</Name>
    <Name category_ref="6" >Стоянки</Name>
    <Name category_ref="7" >У автомагистралей</Name>
    <Name category_ref="8" >Отели и мотели</Name>
    <Name category_ref="9" >Паромы</Name>
    <Name category_ref="10">Погранпереходы</Name>
    <Name category_ref="11">SEAT Сервисные центры</Name>
    <Name category_ref="12">SEAT Дилеры</Name>
    <!-- <Name category_ref="13">Пересечения автомаг.</Name> -->
    <Name category_ref="14">Съезды/въезды автом.</Name>
    <Name category_ref="15">Прокат автомобилей</Name>
    <Name category_ref="16">Ж/д вокзалы</Name>
    <!--<Name category_ref="17">Местный транспорт</Name>-->
    <Name category_ref="18">Автобусные остановки</Name>
    <Name category_ref="19">Инф. для туристов</Name>
    <Name category_ref="20">Полиция/милиция</Name>
    <Name category_ref="21">Больницы</Name>
    <Name category_ref="22">Медицинск.учреждения</Name>
    <Name category_ref="23">Аптеки</Name>
    <Name category_ref="24">Рестораны</Name>
    <Name category_ref="25">Банкоматы</Name>
    <Name category_ref="26">Кафе</Name>
    <Name category_ref="27">Торговые центры</Name>
    <Name category_ref="28">Одежда</Name>
    <Name category_ref="29">Электроника</Name>
    <Name category_ref="30">Вина и крепкие напитки</Name>
    <Name category_ref="31">Ночная жизнь</Name>
    <Name category_ref="32">Парки</Name>
    <Name category_ref="33">Достопримечательн.</Name>
    <Name category_ref="34">Кинотеатры</Name>
    <Name category_ref="35">Казино</Name>
    <Name category_ref="36">Театры, концерт. залы</Name>
    <Name category_ref="37">Музеи</Name>
    <Name category_ref="38">Памятники</Name>
    <Name category_ref="39">Спортивные центры</Name>
    <!-- <Name category_ref="40">Спортивный аэродром</Name> -->
    <Name category_ref="41">Гольф</Name>
    <Name category_ref="42">Лодочный спорт</Name>
    <Name category_ref="43">Лыжи</Name>
    <Name category_ref="44">Парки культ. и отдыха</Name>
    <Name category_ref="45">Банки</Name>
    <Name category_ref="46">Отделения связи</Name>
    <Name category_ref="47">Фирмы</Name>
    <Name category_ref="48">Конгресс-центры</Name>
    <Name category_ref="49">Правит., органы управл.</Name>
    <Name category_ref="50">Посольства</Name>
    <!-- <Name category_ref="51">Органы самоуправлен.</Name> -->
    <Name category_ref="52">Образоват. учреждения</Name>
    <Name category_ref="53">Церкви</Name>
    <Name category_ref="54">Кладбища</Name>
    <Name category_ref="55">Зарядные станции</Name>
  </PoiCategoryNameDefinition>

</LanguagePoiConfiguration>